CCMetrics/CC_base.py
CCMetrics/CC_base_gpu.py
CCMetrics/__init__.py
CCMetrics/space_separation.py
CCMetrics/space_separation_on_gpu.py
ccmetrics-0.0.3.dist-info/licenses/LICENSE
ccmetrics-0.0.3.dist-info/METADATA
ccmetrics-0.0.3.dist-info/WHEEL
ccmetrics-0.0.3.dist-info/top_level.txt
ccmetrics-0.0.3.dist-info/RECORD
