Metadata-Version: 2.4
Name: CCMetrics
Version: 0.0.3
Summary: An evaluation protocol for standard metrics per connected component
Author-email: Alexander Jaus <alexander.jaus@kit.edu>
License-Expression: MIT AND (Apache-2.0 OR BSD-2-Clause)
Project-URL: Homepage, https://github.com/alexanderjaus/CC-Metrics
Project-URL: Issues, https://github.com/alexanderjaus/CC-Metrics/issues
Keywords: medical segmentation,tumor segmentation,instance segmentation,detection via segmentation
Classifier: Development Status :: 4 - Beta
Classifier: Intended Audience :: Science/Research
Classifier: Programming Language :: Python :: 3
Classifier: Programming Language :: Python :: 3.8
Classifier: Topic :: Scientific/Engineering :: Medical Science Apps.
Requires-Python: >=3.8
License-File: LICENSE
Requires-Dist: torch
Requires-Dist: monai
Requires-Dist: numpy
Requires-Dist: scipy
Requires-Dist: connected-components-3d
Requires-Dist: nibabel
Requires-Dist: tqdm
Provides-Extra: test
Requires-Dist: pytest; extra == "test"
Provides-Extra: gpu
Requires-Dist: cupy-cuda12x; extra == "gpu"
Provides-Extra: all
Requires-Dist: pytest; extra == "all"
Requires-Dist: cupy-cuda12x; extra == "all"
Dynamic: license-file
